{"900178184": {"nama": "TPS 01", "dapil": [3102, 13107, null]}, "900178185": {"nama": "TPS 02", "dapil": [3102, 13107, null]}, "900178186": {"nama": "TPS 03", "dapil": [3102, 13107, null]}, "900178187": {"nama": "TPS 04", "dapil": [3102, 13107, null]}, "900178188": {"nama": "TPS 05", "dapil": [3102, 13107, null]}, "900178189": {"nama": "TPS 06", "dapil": [3102, 13107, null]}, "900178190": {"nama": "TPS 07", "dapil": [3102, 13107, null]}, "900178191": {"nama": "TPS 08", "dapil": [3102, 13107, null]}, "900178192": {"nama": "TPS 09", "dapil": [3102, 13107, null]}, "900178193": {"nama": "TPS 10", "dapil": [3102, 13107, null]}, "900178194": {"nama": "TPS 11", "dapil": [3102, 13107, null]}, "900178195": {"nama": "TPS 12", "dapil": [3102, 13107, null]}, "900178196": {"nama": "TPS 13", "dapil": [3102, 13107, null]}, "900178197": {"nama": "TPS 14", "dapil": [3102, 13107, null]}, "900178198": {"nama": "TPS 15", "dapil": [3102, 13107, null]}, "900178199": {"nama": "TPS 16", "dapil": [3102, 13107, null]}, "900178200": {"nama": "TPS 17", "dapil": [3102, 13107, null]}, "900178201": {"nama": "TPS 18", "dapil": [3102, 13107, null]}, "900178202": {"nama": "TPS 19", "dapil": [3102, 13107, null]}, "900178203": {"nama": "TPS 20", "dapil": [3102, 13107, null]}, "900178204": {"nama": "TPS 21", "dapil": [3102, 13107, null]}, "900178205": {"nama": "TPS 22", "dapil": [3102, 13107, null]}, "900178206": {"nama": "TPS 23", "dapil": [3102, 13107, null]}, "900178207": {"nama": "TPS 24", "dapil": [3102, 13107, null]}, "900178208": {"nama": "TPS 25", "dapil": [3102, 13107, null]}, "900178209": {"nama": "TPS 26", "dapil": [3102, 13107, null]}, "900178210": {"nama": "TPS 27", "dapil": [3102, 13107, null]}, "900178211": {"nama": "TPS 28", "dapil": [3102, 13107, null]}, "900178212": {"nama": "TPS 29", "dapil": [3102, 13107, null]}, "900178213": {"nama": "TPS 30", "dapil": [3102, 13107, null]}, "900178214": {"nama": "TPS 31", "dapil": [3102, 13107, null]}, "900178215": {"nama": "TPS 32", "dapil": [3102, 13107, null]}}